paramtree/__init__.py
paramtree/paramtree.py
paramtree-0.1.0.dist-info/METADATA
paramtree-0.1.0.dist-info/WHEEL
paramtree-0.1.0.dist-info/top_level.txt
paramtree-0.1.0.dist-info/RECORD
