Metadata-Version: 2.1
Name: paramtree
Version: 0.1.0
Summary: Store parameter values in a tree
Home-page: UNKNOWN
Author: Jesse Slim
Author-email: jesse.j.slim@gmail.com
License: UNKNOWN
Platform: UNKNOWN
Classifier: Programming Language :: Python :: 3
Classifier: License :: OSI Approved :: MIT License
Classifier: Operating System :: OS Independent
